mkdocs_mermaid_export_to_svg_plugin/__init__.py
mkdocs_mermaid_export_to_svg_plugin/gitinfo.py
mkdocs_mermaid_export_to_svg_plugin/plugin.py
mkdocs_mermaid_export_to_svg-0.2.4.dist-info/LICENSE
mkdocs_mermaid_export_to_svg-0.2.4.dist-info/METADATA
mkdocs_mermaid_export_to_svg-0.2.4.dist-info/WHEEL
mkdocs_mermaid_export_to_svg-0.2.4.dist-info/entry_points.txt
mkdocs_mermaid_export_to_svg-0.2.4.dist-info/top_level.txt
mkdocs_mermaid_export_to_svg-0.2.4.dist-info/RECORD
