Metadata-Version: 2.1
Name: mkdocs-mermaid-export-to-svg
Version: 0.2.4
Summary: MkDocs plugin for showing a history log for a specified markdown file
Home-page: https://github.com/pawelsikora/mkdocs-export-mermaid-to-svg/
Author: Pawel Sikora
Author-email: sikor6@gmail.com
License: MIT
Keywords: mkdocs git meta yaml frontmatter
Platform: UNKNOWN
Requires-Python: >=3.6
Requires-Dist: mkdocs (>=1.1)
Requires-Dist: GitPython
Requires-Dist: jinja2
